CHANGES.txt
LICENSE.txt
MANIFEST.in
README.txt
bootstrap.py
buildout.cfg
setup.py
src/p01/__init__.py
src/p01.geo.egg-info/PKG-INFO
src/p01.geo.egg-info/SOURCES.txt
src/p01.geo.egg-info/dependency_links.txt
src/p01.geo.egg-info/namespace_packages.txt
src/p01.geo.egg-info/not-zip-safe
src/p01.geo.egg-info/requires.txt
src/p01.geo.egg-info/top_level.txt
src/p01/geo/README.txt
src/p01/geo/__init__.py
src/p01/geo/interfaces.py
src/p01/geo/locator.py
src/p01/geo/performance.txt
src/p01/geo/testing.py
src/p01/geo/tests.py
src/p01/geo/data/COPYRIGHT.txt
src/p01/geo/data/GeoLite2-City.zip
src/p01/geo/data/LICENSE.txt
src/p01/geo/data/README.txt